pysubstitutor/__init__.py
pysubstitutor/__main__.py
pysubstitutor/converters/__init__.py
pysubstitutor/converters/converter_interface.py
pysubstitutor/converters/file_converter.py
pysubstitutor/handlers/__init__.py
pysubstitutor/handlers/format_handler.py
pysubstitutor/handlers/gboard_handler.py
pysubstitutor/handlers/markdown_handler.py
pysubstitutor/handlers/plist_handler.py
pysubstitutor/models/__init__.py
pysubstitutor/models/text_substitution.py
pysubstitutor/utils/__init__.py
pysubstitutor/utils/handler_selector.py
pysubstitutor/utils/zip_util.py
pysubstitutor-1.0.2.dist-info/licenses/LICENSE
pysubstitutor-1.0.2.dist-info/METADATA
pysubstitutor-1.0.2.dist-info/WHEEL
pysubstitutor-1.0.2.dist-info/entry_points.txt
pysubstitutor-1.0.2.dist-info/top_level.txt
pysubstitutor-1.0.2.dist-info/RECORD
