Metadata-Version: 2.4
Name: pysubstitutor
Version: 1.0.2
Summary: A Python package for converting text substitution files between different formats.
Home-page: https://github.com/crsiebler/pysubstitutor
Author: Cory Siebler
Author-email: cory.siebler@protonmail.com
Classifier: Programming Language :: Python :: 3
Classifier: License :: OSI Approved :: MIT License
Classifier: Operating System :: OS Independent
Requires-Python: >=3.7
License-File: LICENSE
Requires-Dist: pytest==7.4.2
Requires-Dist: coverage==7.8.0
Requires-Dist: isort==5.12.0
Requires-Dist: black==23.9.1
Dynamic: author
Dynamic: author-email
Dynamic: classifier
Dynamic: description
Dynamic: description-content-type
Dynamic: home-page
Dynamic: license-file
Dynamic: requires-dist
Dynamic: requires-python
Dynamic: summary
